nautobot_floor_plan/__init__.py
nautobot_floor_plan/api/__init__.py
nautobot_floor_plan/api/serializers.py
nautobot_floor_plan/api/urls.py
nautobot_floor_plan/api/views.py
nautobot_floor_plan/app-config-schema.json
nautobot_floor_plan/choices.py
nautobot_floor_plan/custom_panels.py
nautobot_floor_plan/filter_extensions.py
nautobot_floor_plan/filters.py
nautobot_floor_plan/forms.py
nautobot_floor_plan/homepage.py
nautobot_floor_plan/migrations/0001_initial.py
nautobot_floor_plan/migrations/0002_fixup_null.py
nautobot_floor_plan/migrations/0003_auto_20230908_1339.py
nautobot_floor_plan/migrations/0004_auto_20240321_1438.py
nautobot_floor_plan/migrations/0005_add_rackgroup.py
nautobot_floor_plan/migrations/0006_alter_floorplantile_status.py
nautobot_floor_plan/migrations/0007_add_axis_origin_seed.py
nautobot_floor_plan/migrations/0008_add_axis_step.py
nautobot_floor_plan/migrations/0009_add_custom_label_support.py
nautobot_floor_plan/migrations/0010_add_floorplantile_objects.py
nautobot_floor_plan/migrations/__init__.py
nautobot_floor_plan/models.py
nautobot_floor_plan/navigation.py
nautobot_floor_plan/signals.py
nautobot_floor_plan/static/nautobot_floor_plan/css/dark_svg.css
nautobot_floor_plan/static/nautobot_floor_plan/css/light.css
nautobot_floor_plan/static/nautobot_floor_plan/css/svg.css
nautobot_floor_plan/static/nautobot_floor_plan/docs/404.html
nautobot_floor_plan/static/nautobot_floor_plan/docs/admin/compatibility_matrix.html
nautobot_floor_plan/static/nautobot_floor_plan/docs/admin/install.html
nautobot_floor_plan/static/nautobot_floor_plan/docs/admin/release_notes/index.html
nautobot_floor_plan/static/nautobot_floor_plan/docs/admin/release_notes/version_1.0.html
nautobot_floor_plan/static/nautobot_floor_plan/docs/admin/release_notes/version_2.0.html
nautobot_floor_plan/static/nautobot_floor_plan/docs/admin/release_notes/version_2.1.html
nautobot_floor_plan/static/nautobot_floor_plan/docs/admin/release_notes/version_2.2.html
nautobot_floor_plan-2.8.1.dist-info/LICENSE
nautobot_floor_plan-2.8.1.dist-info/METADATA
nautobot_floor_plan-2.8.1.dist-info/WHEEL
nautobot_floor_plan-2.8.1.dist-info/RECORD
