Metadata-Version: 2.1
Name: nautobot-floor-plan
Version: 2.8.1
Summary: Nautobot Floor Plan
Home-page: https://github.com/nautobot/nautobot-app-floor-plan
License: Apache-2.0
Keywords: nautobot,nautobot-app,nautobot-plugin
Author: Network to Code, LLC
Author-email: info@networktocode.com
Requires-Python: >=3.9.2,<3.13
Classifier: Development Status :: 5 - Production/Stable
Classifier: Intended Audience :: Developers
Classifier: License :: OSI Approved :: Apache Software License
Classifier: Programming Language :: Python :: 3
Classifier: Programming Language :: Python :: 3.10
Classifier: Programming Language :: Python :: 3.11
Classifier: Programming Language :: Python :: 3.12
Classifier: Programming Language :: Python :: 3.9
Provides-Extra: all
Requires-Dist: nautobot (>=2.4.0,<3.0.0)
Project-URL: Documentation, https://docs.nautobot.com/projects/floor-plan/en/latest/
Project-URL: Repository, https://github.com/nautobot/nautobot-app-floor-plan
